kuzbara/__init__.py
kuzbara/domain.py
kuzbara/exceptions.py
kuzbara/main.py
kuzbara/runner.py
kuzbara/utils.py
kuzbara/adapters/__init__.py
kuzbara/adapters/fastapi.py
kuzbara/observers/__init__.py
kuzbara/probes/__init__.py
kuzbara/probes/base.py
kuzbara/probes/http.py
kuzbara/probes/redis.py
kuzbara/probes/sql.py
kuzbara/probes/system.py
kuzbara-0.1.0.dist-info/METADATA
kuzbara-0.1.0.dist-info/WHEEL
kuzbara-0.1.0.dist-info/licenses/LICENSE
kuzbara-0.1.0.dist-info/RECORD
