Metadata-Version: 2.4
Name: kuzbara
Version: 0.1.0
Summary: Fresh, organic health checks for Python.Smooth, probiotic health checks for Python.
Author-email: suaue <suaue@users.noreply.github.com>
License-Expression: MIT
License-File: LICENSE
Requires-Python: >=3.9
Provides-Extra: dev
Requires-Dist: fastapi; extra == 'dev'
Requires-Dist: flask; extra == 'dev'
Requires-Dist: httpx; extra == 'dev'
Requires-Dist: pytest; extra == 'dev'
Requires-Dist: pytest-asyncio; extra == 'dev'
Provides-Extra: http
Requires-Dist: httpx>=0.24; extra == 'http'
Provides-Extra: system
Requires-Dist: psutil>=5.0; extra == 'system'
